gtsocket/__init__.py
gtsocket/gtsocket.cfg
gtsocket/gtsocket.py
gtsocket/tests/__init__.py
gtsocket/tests/test_encoding.py
gtsocket/tests/test_socket.py
gtsocket-0.1.data/scripts/gtsocket-setup
gtsocket-0.1.data/scripts/gtsocket-test
gtsocket-0.1.dist-info/LICENSE.txt
gtsocket-0.1.dist-info/METADATA
gtsocket-0.1.dist-info/WHEEL
gtsocket-0.1.dist-info/top_level.txt
gtsocket-0.1.dist-info/RECORD
