Metadata-Version: 2.1
Name: gtsocket
Version: 0.1
Summary: Receive and/or send commands to radio controlled sockets (model GT-FSI-11) from brand "Globaltronics".
Home-page: https://github.com/funkesoftware/gtsocket
Author: Markus Funke
Author-email: gtsocket@funke-software.de
License: GPLv3+
Keywords: radio socket 433Mhz Globaltronics GT-FSI-11 RPi EasyHome
Platform: UNKNOWN
Classifier: Development Status :: 4 - Beta
Classifier: Intended Audience :: Developers
Classifier: License :: OSI Approved :: GNU General Public License v3 or later (GPLv3+)
Classifier: Operating System :: POSIX :: Linux
Classifier: Programming Language :: Python :: 2.7
Classifier: Programming Language :: Python :: 3
Classifier: Topic :: Communications
Classifier: Topic :: Home Automation
Requires-Dist: configparser
Requires-Dist: future
